mediameta/__init__.py
mediameta/dataroutines.py
mediameta/imagemetadata.py
mediameta/mediametadata.py
mediameta/tags.py
mediameta/videometadata.py
mediameta-0.2.0.dist-info/METADATA
mediameta-0.2.0.dist-info/WHEEL
mediameta-0.2.0.dist-info/licenses/LICENSE
mediameta-0.2.0.dist-info/RECORD
