Metadata-Version: 2.4
Name: mediameta
Version: 0.2.0
Summary: Photo and Video metadata parsing package
Project-URL: Homepage, https://github.com/dandelion-systems/mediameta
Project-URL: Bug Tracker, https://github.com/dandelion-systems/mediameta/issues
Author-email: Dandelion Systems <dandelion.systems@gmail.com>
License-File: LICENSE
Keywords: EXIF,GPS,Google maps,HEIC,JPEG,JPG,MOV,QuickTime,TIF,TIFF,Yandex maps,maps,metadata,parsing
Classifier: License :: OSI Approved :: MIT License
Classifier: Operating System :: OS Independent
Classifier: Programming Language :: Python :: 3
Requires-Python: >=3.9
